Metadata-Version: 1.1
Name: disbotapipy
Version: 1.9.2
Summary: A simple Python module for the disbot.top service
Home-page: https://github.com/Smirf123/disbotapipy
Author: Smirf123
Author-email: matthewelert@gmail.com
License: MIT
Download-URL: https://github.com/Smirf123/disbotapipy/archive/v1.9.2.tar.gz
Keywords: disbot,discord,bot
Platform: UNKNOWN
Classifier: Development Status :: 5 - Production/Stable
Classifier: Intended Audience :: Developers
Classifier: Topic :: Software Development :: Build Tools
Classifier: License :: OSI Approved :: MIT License
Classifier: Programming Language :: Python :: 3
Classifier: Programming Language :: Python :: 3.4
Classifier: Programming Language :: Python :: 3.5
Classifier: Programming Language :: Python :: 3.6
